komandr.py
komandr-2.0.1.dist-info/METADATA
komandr-2.0.1.dist-info/WHEEL
komandr-2.0.1.dist-info/top_level.txt
komandr-2.0.1.dist-info/RECORD
