Metadata-Version: 2.1
Name: komandr
Version: 2.0.1
Summary: Coolest command-line interface on this planet
Home-page: https://github.com/kadirpekel/komandr
Author: Kadir Pekel
Author-email: kadirpekel@gmail.com
License: UNKNOWN
Platform: UNKNOWN
Requires-Python: >3.5.4
